dialz/__init__.py
dialz/dataset.py
dialz/datasets/create/age.json
dialz/datasets/create/disability.json
dialz/datasets/create/gender.json
dialz/datasets/create/question-answer.json
dialz/datasets/create/race.json
dialz/datasets/create/religion.json
dialz/datasets/create/sentence-starters.json
dialz/datasets/create/sexuality.json
dialz/datasets/create/socioeconomic.json
dialz/datasets/create/tasks.json
dialz/datasets/load/coordinate-other-ais.json
dialz/datasets/load/corrigible-neutral-HHH.json
dialz/datasets/load/hallucination.json
dialz/datasets/load/morality.json
dialz/datasets/load/myopic-reward.json
dialz/datasets/load/refusal.json
dialz/datasets/load/stereoset-gender.json
dialz/datasets/load/stereoset-profession.json
dialz/datasets/load/stereoset-race.json
dialz/datasets/load/stereoset-religion.json
dialz/datasets/load/survival-instinct.json
dialz/datasets/load/sycophancy.json
dialz/score.py
dialz/vector.py
dialz/visualize.py
dialz-1.1.4.dist-info/LICENSE
dialz-1.1.4.dist-info/METADATA
dialz-1.1.4.dist-info/WHEEL
dialz-1.1.4.dist-info/RECORD
