Metadata-Version: 2.3
Name: dialz
Version: 1.1.4
Summary: 
Author: groovychoons
Author-email: siddiquezs2@cardiff.ac.uk
Requires-Python: >=3.10,<4.0
Classifier: Programming Language :: Python :: 3
Classifier: Programming Language :: Python :: 3.10
Classifier: Programming Language :: Python :: 3.11
Classifier: Programming Language :: Python :: 3.12
Classifier: Programming Language :: Python :: 3.13
Requires-Dist: accelerate (>=1.1.1,<2.0.0)
Requires-Dist: gguf (>=0.13.0,<0.14.0)
Requires-Dist: python-dotenv (>=1.0.1,<2.0.0)
Requires-Dist: scikit-learn (>=1.6.0,<2.0.0)
Requires-Dist: torch (>=2.5.1,<3.0.0)
Requires-Dist: transformers (>=4.46.3,<5.0.0)
